{
    "Reflectivity": [
        "Reflectivity_2026-04-11_190000.png",
        "Reflectivity_2026-04-11_194800.png",
        "Reflectivity_2026-04-11_204000.png",
        "Reflectivity_2026-04-11_211400.png",
        "Reflectivity_2026-04-11_215600.png",
        "Reflectivity_2026-04-11_224200.png",
        "Reflectivity_2026-04-11_231600.png",
        "Reflectivity_2026-04-12_034000.png",
        "Reflectivity_2026-04-12_054600.png",
        "Reflectivity_2026-04-12_072000.png",
        "Reflectivity_2026-04-12_081000.png",
        "Reflectivity_2026-04-12_090600.png",
        "Reflectivity_2026-04-12_100200.png",
        "Reflectivity_2026-04-12_110000.png",
        "Reflectivity_2026-04-12_114800.png"
    ],
    "PrecipType": [],
    "Rotation_1hr": [],
    "Rotation_Instant": [],
    "MESH": [],
    "PrecipRate": [],
    "QPE_1hr": [],
    "QPE_6hr": [],
    "QPE_24hr": []
}