{
    "Reflectivity": [
        "Reflectivity_2026-05-10_194400.png",
        "Reflectivity_2026-05-10_205400.png",
        "Reflectivity_2026-05-10_215200.png",
        "Reflectivity_2026-05-10_225200.png",
        "Reflectivity_2026-05-10_235600.png",
        "Reflectivity_2026-05-11_041400.png",
        "Reflectivity_2026-05-11_080000.png",
        "Reflectivity_2026-05-11_113600.png",
        "Reflectivity_2026-05-11_141000.png",
        "Reflectivity_2026-05-11_164600.png",
        "Reflectivity_2026-05-11_185800.png"
    ],
    "PrecipType": [],
    "Rotation_1hr": [],
    "Rotation_Instant": [],
    "MESH": [],
    "PrecipRate": [],
    "QPE_1hr": [],
    "QPE_6hr": [],
    "QPE_24hr": []
}